stelspec/__init__.py
stelspec/columns.py
stelspec/core.py
stelspec-0.0.5.dist-info/LICENSE.txt
stelspec-0.0.5.dist-info/METADATA
stelspec-0.0.5.dist-info/WHEEL
stelspec-0.0.5.dist-info/top_level.txt
stelspec-0.0.5.dist-info/RECORD
