Metadata-Version: 2.1
Name: stelspec
Version: 0.0.5
Summary: A python package for retrieving and analysing stellar spectra (ELODIE-SOPHIE Archive)
Home-page: https://github.com/behrouzz/stelspec
Author: Behrouz Safari
Author-email: behrouz.safari@gmail.com
License: MIT
Platform: UNKNOWN
Classifier: Programming Language :: Python :: 3
Classifier: License :: OSI Approved :: MIT License
Classifier: Operating System :: OS Independent
Requires-Python: >=3.4
License-File: LICENSE.txt
Requires-Dist: requests
Requires-Dist: numpy
Requires-Dist: pandas
